numpyUtilsUpdated/__init__.py
numpyUtilsUpdated/ai/AlphaBetaPr.py
numpyUtilsUpdated/ai/BFS_8pz.py
numpyUtilsUpdated/ai/DFS_8pz.py
numpyUtilsUpdated/ai/DLimitS_8pz.py
numpyUtilsUpdated/ai/GBFS.py
numpyUtilsUpdated/ai/GraphColor.py
numpyUtilsUpdated/ai/Minimax.py
numpyUtilsUpdated/ai/Prologs.py
numpyUtilsUpdated/ai/UCS.py
numpyUtilsUpdated/ai/VaccumCleaner.py
numpyUtilsUpdated/ai/Wumpus.py
numpyUtilsUpdated/ai/__init__.py
numpyUtilsUpdated/ai/ticTacToe.py
numpyUtilsUpdated/ai/waterJug.py
numpyUtilsUpdated/aib/BFS1.py
numpyUtilsUpdated/aib/Best_First_search1.py
numpyUtilsUpdated/aib/DFS1.py
numpyUtilsUpdated/aib/DLS1.py
numpyUtilsUpdated/aib/Graph_coloring1.py
numpyUtilsUpdated/aib/Greedy_BFS1.py
numpyUtilsUpdated/aib/Minimax_Tic_Tac_Toe1.py
numpyUtilsUpdated/aib/UCS1.py
numpyUtilsUpdated/aib/Vaccum_World1.py
numpyUtilsUpdated/aib/Water_jug1.py
numpyUtilsUpdated/aib/Wumpus_World1.py
numpyUtilsUpdated/aib/__init__.py
numpyUtilsUpdated/cs/__init__.py
numpyUtilsUpdated/cs/ass1.py
numpyUtilsUpdated/cs/ass2.py
numpyUtilsUpdated/cs/ass3.py
numpyUtilsUpdated/cs/ass4.py
numpyUtilsUpdated/cs/ass5.py
numpyUtilsUpdated/cs/ass6.py
numpyUtilsUpdated/daa/APSP_floyd_warshall.py
numpyUtilsUpdated/daa/BinarySearch.py
numpyUtilsUpdated/daa/Dijkstras.py
numpyUtilsUpdated/daa/Greedy_01knapsack.py
numpyUtilsUpdated/daa/Greedy_FKanpsack.py
numpyUtilsUpdated/daa/Job_Seq.py
numpyUtilsUpdated/daa/KnapDP.py
numpyUtilsUpdated/daa/Kruskals.py
numpyUtilsUpdated/daa/Matrix.py
numpyUtilsUpdated/daa/Prims.py
numpyUtilsUpdated/daa/Quick_Sort.py
numpyUtilsUpdated/daa/SSSP_bellman_ford.py
numpyUtilsUpdated/daa/String_editing_problem.py
numpyUtilsUpdated/daa/TSP.py
numpyUtilsUpdated/daa/__init__.py
numpyUtilsUpdated/daa/getInfo.py
numpyUtilsUpdated/daa/min_max.py
numpyUtilsUpdated/daaNew/Prog1.py
numpyUtilsUpdated/daaNew/Prog10.py
numpyUtilsUpdated/daaNew/Prog11.py
numpyUtilsUpdated/daaNew/Prog12.py
numpyUtilsUpdated/daaNew/Prog2.py
numpyUtilsUpdated/daaNew/Prog3.py
numpyUtilsUpdated/daaNew/Prog4.py
numpyutilsupdated-0.0.5.dist-info/METADATA
numpyutilsupdated-0.0.5.dist-info/WHEEL
numpyutilsupdated-0.0.5.dist-info/licenses/LICENSE
numpyutilsupdated-0.0.5.dist-info/RECORD
