Metadata-Version: 2.4
Name: numpyUtilsUpdated
Version: 0.0.5
Summary: A collection of numpy utilities for data analysis and manipulation.
Project-URL: Homepage, https://github.com/nani-here/numpyUtilsUpdated
Project-URL: Issues, https://github.com/nani-here/numpyUtilsUpdated/issues
Author-email: Nani bolthe! <neku.enduku2005@gmail.com>
License-File: LICENSE
Classifier: License :: OSI Approved :: GNU General Public License v3 (GPLv3)
Classifier: Operating System :: OS Independent
Classifier: Programming Language :: Python :: 3
Requires-Python: >=3.0
